logging_journald.py
logging_journald-0.6.10.dist-info/COPYING
logging_journald-0.6.10.dist-info/METADATA
logging_journald-0.6.10.dist-info/WHEEL
logging_journald-0.6.10.dist-info/RECORD
