Metadata-Version: 2.1
Name: logging-journald
Version: 0.6.10
Summary: Pure python logging handler for writing logs to the journald using native protocol
Home-page: https://github.com/mosquito/logging-journald
License: MIT
Author: Dmitry Orlov
Author-email: me@mosquito.su
Requires-Python: >=3.8,<4.0
Classifier: Intended Audience :: Developers
Classifier: License :: OSI Approved :: MIT License
Classifier: Operating System :: POSIX :: Linux
Classifier: Programming Language :: Python
Classifier: Programming Language :: Python :: 3
Classifier: Programming Language :: Python :: 3.8
Classifier: Programming Language :: Python :: 3.9
Classifier: Programming Language :: Python :: 3.10
Classifier: Programming Language :: Python :: 3.11
Classifier: Programming Language :: Python :: 3.12
Classifier: Programming Language :: Python :: Implementation :: CPython
Project-URL: Source, https://github.com/mosquito/logging-journald
Project-URL: Tracker, https://github.com/mosquito/logging-journald/issues
